natsume/DeckAgol.py
natsume/Lithwick.py
natsume/__init__.py
natsume/classes.py
natsume/common.py
natsume_ttv-0.1.3.dist-info/licenses/LICENSE
natsume_ttv-0.1.3.dist-info/METADATA
natsume_ttv-0.1.3.dist-info/WHEEL
natsume_ttv-0.1.3.dist-info/top_level.txt
natsume_ttv-0.1.3.dist-info/RECORD
