Metadata-Version: 2.4
Name: natsume-ttv
Version: 0.1.3
Summary: Near-resonant Analytic TTV Solver for Unknown Mass Estimates
Author-email: Chatdanai Sawangwong <chatdanai.saw@student.mahidol.edu>
License: MIT
Project-URL: Homepage, https://github.com/chatdanai-s/NATSUME
Project-URL: BugTracker, https://github.com/chatdanai-s/NATSUME/issues
Keywords: ttv,mmr,exoplanets
Classifier: Programming Language :: Python :: 3
Classifier: Operating System :: OS Independent
Requires-Python: >=3.7
License-File: LICENSE
Requires-Dist: numpy>=1.25
Requires-Dist: scipy>=1.12
Dynamic: license-file
